argparse_range/__init__.py
argparse_range/py.typed
argparse_range-0.1.2.dist-info/WHEEL
argparse_range-0.1.2.dist-info/METADATA
argparse_range-0.1.2.dist-info/RECORD
