Metadata-Version: 2.1
Name: argparse-range
Version: 0.1.2
Summary: Numeric range for argparse arguments
Home-page: https://github.com/aatifsyed/argparse-range
License: MIT
Author: Aatif Syed
Author-email: aatifsyedyp@gmail.com
Requires-Python: >=3.8,<4.0
Classifier: License :: OSI Approved :: MIT License
Classifier: Programming Language :: Python :: 3
Classifier: Programming Language :: Python :: 3.10
Classifier: Programming Language :: Python :: 3.8
Classifier: Programming Language :: Python :: 3.9
Project-URL: Repository, https://github.com/aatifsyed/argparse-range
